{
  "0": {
    "clean_topk": [
      [
        1,
        0.16666666666666666
      ],
      [
        2,
        0.21428571428571427
      ],
      [
        3,
        0.21428571428571427
      ]
    ],
    "clean_rank_list": [
      153,
      10,
      45,
      4,
      4,
      5,
      44,
      461,
      107,
      0,
      47,
      3,
      61,
      62,
      24,
      142,
      1,
      0,
      4,
      17,
      34,
      15,
      0,
      186,
      0,
      18,
      47,
      8,
      1,
      23,
      114,
      0,
      0,
      0,
      16,
      40,
      16,
      14,
      42,
      57,
      7,
      59
    ],
    "intervention_topk": [
      [
        1,
        0.3333333333333333
      ],
      [
        2,
        0.42857142857142855
      ],
      [
        3,
        0.42857142857142855
      ]
    ],
    "intervention_rank_list": [
      129,
      11,
      12,
      0,
      0,
      0,
      15,
      1023,
      33,
      0,
      24,
      0,
      3,
      1,
      38,
      45,
      0,
      0,
      3,
      4,
      70,
      16,
      0,
      39,
      0,
      0,
      14,
      1,
      1,
      15,
      84,
      0,
      0,
      0,
      8,
      4,
      21,
      7,
      37,
      49,
      1,
      0
    ]
  },
  "1": {
    "clean_topk": [
      [
        1,
        0.16666666666666666
      ],
      [
        2,
        0.21428571428571427
      ],
      [
        3,
        0.21428571428571427
      ]
    ],
    "clean_rank_list": [
      153,
      10,
      45,
      4,
      4,
      5,
      44,
      461,
      107,
      0,
      47,
      3,
      61,
      62,
      24,
      142,
      1,
      0,
      4,
      17,
      34,
      15,
      0,
      186,
      0,
      18,
      47,
      8,
      1,
      23,
      114,
      0,
      0,
      0,
      16,
      40,
      16,
      14,
      42,
      57,
      7,
      59
    ],
    "intervention_topk": [
      [
        1,
        0.35714285714285715
      ],
      [
        2,
        0.47619047619047616
      ],
      [
        3,
        0.5
      ]
    ],
    "intervention_rank_list": [
      127,
      4,
      1,
      0,
      0,
      0,
      15,
      676,
      7,
      0,
      17,
      0,
      3,
      0,
      17,
      18,
      0,
      0,
      3,
      2,
      29,
      12,
      0,
      27,
      0,
      0,
      7,
      1,
      1,
      14,
      73,
      0,
      0,
      0,
      6,
      1,
      17,
      6,
      14,
      41,
      1,
      0
    ]
  },
  "2": {
    "clean_topk": [
      [
        1,
        0.16666666666666666
      ],
      [
        2,
        0.21428571428571427
      ],
      [
        3,
        0.21428571428571427
      ]
    ],
    "clean_rank_list": [
      153,
      10,
      45,
      4,
      4,
      5,
      44,
      461,
      107,
      0,
      47,
      3,
      61,
      62,
      24,
      142,
      1,
      0,
      4,
      17,
      34,
      15,
      0,
      186,
      0,
      18,
      47,
      8,
      1,
      23,
      114,
      0,
      0,
      0,
      16,
      40,
      16,
      14,
      42,
      57,
      7,
      59
    ],
    "intervention_topk": [
      [
        1,
        0.23809523809523808
      ],
      [
        2,
        0.30952380952380953
      ],
      [
        3,
        0.35714285714285715
      ]
    ],
    "intervention_rank_list": [
      148,
      12,
      21,
      0,
      1,
      0,
      19,
      922,
      66,
      0,
      40,
      0,
      8,
      36,
      16,
      119,
      1,
      0,
      4,
      4,
      36,
      32,
      1,
      108,
      0,
      2,
      41,
      2,
      0,
      26,
      101,
      0,
      0,
      0,
      17,
      13,
      27,
      9,
      25,
      53,
      3,
      5
    ]
  },
  "3": {
    "clean_topk": [
      [
        1,
        0.16666666666666666
      ],
      [
        2,
        0.21428571428571427
      ],
      [
        3,
        0.21428571428571427
      ]
    ],
    "clean_rank_list": [
      153,
      10,
      45,
      4,
      4,
      5,
      44,
      461,
      107,
      0,
      47,
      3,
      61,
      62,
      24,
      142,
      1,
      0,
      4,
      17,
      34,
      15,
      0,
      186,
      0,
      18,
      47,
      8,
      1,
      23,
      114,
      0,
      0,
      0,
      16,
      40,
      16,
      14,
      42,
      57,
      7,
      59
    ],
    "intervention_topk": [
      [
        1,
        0.14285714285714285
      ],
      [
        2,
        0.21428571428571427
      ],
      [
        3,
        0.23809523809523808
      ]
    ],
    "intervention_rank_list": [
      160,
      13,
      44,
      3,
      4,
      3,
      49,
      608,
      115,
      0,
      49,
      2,
      46,
      77,
      18,
      130,
      1,
      0,
      4,
      15,
      56,
      27,
      1,
      163,
      0,
      21,
      45,
      9,
      0,
      21,
      111,
      1,
      0,
      0,
      19,
      34,
      24,
      14,
      30,
      59,
      10,
      39
    ]
  },
  "4": {
    "clean_topk": [
      [
        1,
        0.16666666666666666
      ],
      [
        2,
        0.21428571428571427
      ],
      [
        3,
        0.21428571428571427
      ]
    ],
    "clean_rank_list": [
      153,
      10,
      45,
      4,
      4,
      5,
      44,
      461,
      107,
      0,
      47,
      3,
      61,
      62,
      24,
      142,
      1,
      0,
      4,
      17,
      34,
      15,
      0,
      186,
      0,
      18,
      47,
      8,
      1,
      23,
      114,
      0,
      0,
      0,
      16,
      40,
      16,
      14,
      42,
      57,
      7,
      59
    ],
    "intervention_topk": [
      [
        1,
        0.14285714285714285
      ],
      [
        2,
        0.23809523809523808
      ],
      [
        3,
        0.23809523809523808
      ]
    ],
    "intervention_rank_list": [
      150,
      10,
      53,
      5,
      4,
      4,
      54,
      608,
      110,
      0,
      43,
      1,
      42,
      73,
      21,
      151,
      0,
      0,
      4,
      15,
      46,
      27,
      1,
      170,
      0,
      19,
      48,
      9,
      1,
      20,
      117,
      1,
      0,
      0,
      14,
      33,
      15,
      17,
      37,
      56,
      8,
      60
    ]
  },
  "5": {
    "clean_topk": [
      [
        1,
        0.16666666666666666
      ],
      [
        2,
        0.21428571428571427
      ],
      [
        3,
        0.21428571428571427
      ]
    ],
    "clean_rank_list": [
      153,
      10,
      45,
      4,
      4,
      5,
      44,
      461,
      107,
      0,
      47,
      3,
      61,
      62,
      24,
      142,
      1,
      0,
      4,
      17,
      34,
      15,
      0,
      186,
      0,
      18,
      47,
      8,
      1,
      23,
      114,
      0,
      0,
      0,
      16,
      40,
      16,
      14,
      42,
      57,
      7,
      59
    ],
    "intervention_topk": [
      [
        1,
        0.16666666666666666
      ],
      [
        2,
        0.23809523809523808
      ],
      [
        3,
        0.2619047619047619
      ]
    ],
    "intervention_rank_list": [
      154,
      11,
      43,
      3,
      4,
      3,
      50,
      605,
      117,
      0,
      42,
      1,
      28,
      68,
      18,
      149,
      0,
      0,
      2,
      15,
      32,
      25,
      1,
      183,
      0,
      16,
      49,
      11,
      0,
      19,
      112,
      1,
      0,
      0,
      10,
      29,
      15,
      14,
      37,
      52,
      11,
      52
    ]
  },
  "6": {
    "clean_topk": [
      [
        1,
        0.16666666666666666
      ],
      [
        2,
        0.21428571428571427
      ],
      [
        3,
        0.21428571428571427
      ]
    ],
    "clean_rank_list": [
      153,
      10,
      45,
      4,
      4,
      5,
      44,
      461,
      107,
      0,
      47,
      3,
      61,
      62,
      24,
      142,
      1,
      0,
      4,
      17,
      34,
      15,
      0,
      186,
      0,
      18,
      47,
      8,
      1,
      23,
      114,
      0,
      0,
      0,
      16,
      40,
      16,
      14,
      42,
      57,
      7,
      59
    ],
    "intervention_topk": [
      [
        1,
        0.19047619047619047
      ],
      [
        2,
        0.2619047619047619
      ],
      [
        3,
        0.2857142857142857
      ]
    ],
    "intervention_rank_list": [
      144,
      11,
      31,
      5,
      4,
      1,
      39,
      496,
      120,
      0,
      45,
      1,
      20,
      54,
      19,
      139,
      0,
      0,
      2,
      14,
      27,
      29,
      1,
      180,
      0,
      18,
      42,
      9,
      0,
      19,
      108,
      0,
      0,
      0,
      9,
      28,
      25,
      18,
      29,
      47,
      9,
      38
    ]
  },
  "7": {
    "clean_topk": [
      [
        1,
        0.16666666666666666
      ],
      [
        2,
        0.21428571428571427
      ],
      [
        3,
        0.21428571428571427
      ]
    ],
    "clean_rank_list": [
      153,
      10,
      45,
      4,
      4,
      5,
      44,
      461,
      107,
      0,
      47,
      3,
      61,
      62,
      24,
      142,
      1,
      0,
      4,
      17,
      34,
      15,
      0,
      186,
      0,
      18,
      47,
      8,
      1,
      23,
      114,
      0,
      0,
      0,
      16,
      40,
      16,
      14,
      42,
      57,
      7,
      59
    ],
    "intervention_topk": [
      [
        1,
        0.21428571428571427
      ],
      [
        2,
        0.2619047619047619
      ],
      [
        3,
        0.2857142857142857
      ]
    ],
    "intervention_rank_list": [
      151,
      10,
      22,
      5,
      4,
      0,
      30,
      527,
      120,
      0,
      44,
      1,
      5,
      37,
      19,
      124,
      0,
      0,
      2,
      12,
      28,
      34,
      1,
      206,
      0,
      17,
      35,
      6,
      0,
      25,
      106,
      0,
      0,
      0,
      9,
      23,
      24,
      23,
      21,
      49,
      12,
      21
    ]
  },
  "8": {
    "clean_topk": [
      [
        1,
        0.16666666666666666
      ],
      [
        2,
        0.21428571428571427
      ],
      [
        3,
        0.21428571428571427
      ]
    ],
    "clean_rank_list": [
      153,
      10,
      45,
      4,
      4,
      5,
      44,
      461,
      107,
      0,
      47,
      3,
      61,
      62,
      24,
      142,
      1,
      0,
      4,
      17,
      34,
      15,
      0,
      186,
      0,
      18,
      47,
      8,
      1,
      23,
      114,
      0,
      0,
      0,
      16,
      40,
      16,
      14,
      42,
      57,
      7,
      59
    ],
    "intervention_topk": [
      [
        1,
        0.21428571428571427
      ],
      [
        2,
        0.2619047619047619
      ],
      [
        3,
        0.2857142857142857
      ]
    ],
    "intervention_rank_list": [
      149,
      10,
      16,
      4,
      4,
      0,
      15,
      570,
      117,
      0,
      42,
      1,
      4,
      23,
      17,
      105,
      0,
      0,
      2,
      6,
      24,
      33,
      1,
      176,
      0,
      13,
      31,
      4,
      0,
      29,
      95,
      0,
      0,
      0,
      7,
      14,
      19,
      23,
      18,
      45,
      12,
      11
    ]
  },
  "9": {
    "clean_topk": [
      [
        1,
        0.16666666666666666
      ],
      [
        2,
        0.21428571428571427
      ],
      [
        3,
        0.21428571428571427
      ]
    ],
    "clean_rank_list": [
      153,
      10,
      45,
      4,
      4,
      5,
      44,
      461,
      107,
      0,
      47,
      3,
      61,
      62,
      24,
      142,
      1,
      0,
      4,
      17,
      34,
      15,
      0,
      186,
      0,
      18,
      47,
      8,
      1,
      23,
      114,
      0,
      0,
      0,
      16,
      40,
      16,
      14,
      42,
      57,
      7,
      59
    ],
    "intervention_topk": [
      [
        1,
        0.23809523809523808
      ],
      [
        2,
        0.2619047619047619
      ],
      [
        3,
        0.30952380952380953
      ]
    ],
    "intervention_rank_list": [
      149,
      9,
      11,
      2,
      3,
      0,
      19,
      675,
      117,
      0,
      40,
      1,
      3,
      24,
      15,
      100,
      0,
      0,
      2,
      6,
      22,
      37,
      0,
      205,
      0,
      14,
      34,
      6,
      0,
      31,
      100,
      0,
      0,
      0,
      9,
      12,
      14,
      15,
      18,
      44,
      12,
      12
    ]
  },
  "10": {
    "clean_topk": [
      [
        1,
        0.16666666666666666
      ],
      [
        2,
        0.21428571428571427
      ],
      [
        3,
        0.21428571428571427
      ]
    ],
    "clean_rank_list": [
      153,
      10,
      45,
      4,
      4,
      5,
      44,
      461,
      107,
      0,
      47,
      3,
      61,
      62,
      24,
      142,
      1,
      0,
      4,
      17,
      34,
      15,
      0,
      186,
      0,
      18,
      47,
      8,
      1,
      23,
      114,
      0,
      0,
      0,
      16,
      40,
      16,
      14,
      42,
      57,
      7,
      59
    ],
    "intervention_topk": [
      [
        1,
        0.2619047619047619
      ],
      [
        2,
        0.3333333333333333
      ],
      [
        3,
        0.40476190476190477
      ]
    ],
    "intervention_rank_list": [
      141,
      5,
      8,
      2,
      2,
      0,
      9,
      404,
      22,
      0,
      42,
      0,
      2,
      3,
      11,
      93,
      0,
      0,
      1,
      5,
      24,
      13,
      0,
      170,
      0,
      6,
      23,
      1,
      0,
      23,
      92,
      0,
      0,
      0,
      11,
      10,
      11,
      9,
      15,
      28,
      1,
      10
    ]
  },
  "11": {
    "clean_topk": [
      [
        1,
        0.16666666666666666
      ],
      [
        2,
        0.21428571428571427
      ],
      [
        3,
        0.21428571428571427
      ]
    ],
    "clean_rank_list": [
      153,
      10,
      45,
      4,
      4,
      5,
      44,
      461,
      107,
      0,
      47,
      3,
      61,
      62,
      24,
      142,
      1,
      0,
      4,
      17,
      34,
      15,
      0,
      186,
      0,
      18,
      47,
      8,
      1,
      23,
      114,
      0,
      0,
      0,
      16,
      40,
      16,
      14,
      42,
      57,
      7,
      59
    ],
    "intervention_topk": [
      [
        1,
        0.5
      ],
      [
        2,
        0.6904761904761905
      ],
      [
        3,
        0.7142857142857143
      ]
    ],
    "intervention_rank_list": [
      91,
      1,
      1,
      2,
      0,
      0,
      6,
      389,
      0,
      0,
      18,
      0,
      0,
      0,
      4,
      33,
      0,
      0,
      1,
      0,
      1,
      0,
      0,
      96,
      0,
      0,
      4,
      1,
      0,
      0,
      57,
      0,
      0,
      0,
      8,
      0,
      1,
      4,
      10,
      1,
      0,
      1
    ]
  },
  "12": {
    "clean_topk": [
      [
        1,
        0.16666666666666666
      ],
      [
        2,
        0.21428571428571427
      ],
      [
        3,
        0.21428571428571427
      ]
    ],
    "clean_rank_list": [
      153,
      10,
      45,
      4,
      4,
      5,
      44,
      461,
      107,
      0,
      47,
      3,
      61,
      62,
      24,
      142,
      1,
      0,
      4,
      17,
      34,
      15,
      0,
      186,
      0,
      18,
      47,
      8,
      1,
      23,
      114,
      0,
      0,
      0,
      16,
      40,
      16,
      14,
      42,
      57,
      7,
      59
    ],
    "intervention_topk": [
      [
        1,
        0.7380952380952381
      ],
      [
        2,
        0.8333333333333334
      ],
      [
        3,
        0.8333333333333334
      ]
    ],
    "intervention_rank_list": [
      80,
      0,
      0,
      0,
      0,
      0,
      3,
      195,
      0,
      0,
      3,
      0,
      0,
      0,
      0,
      13,
      0,
      0,
      1,
      0,
      0,
      0,
      0,
      8,
      0,
      0,
      0,
      1,
      0,
      0,
      33,
      0,
      0,
      0,
      1,
      0,
      0,
      0,
      1,
      0,
      0,
      0
    ]
  },
  "13": {
    "clean_topk": [
      [
        1,
        0.16666666666666666
      ],
      [
        2,
        0.21428571428571427
      ],
      [
        3,
        0.21428571428571427
      ]
    ],
    "clean_rank_list": [
      153,
      10,
      45,
      4,
      4,
      5,
      44,
      461,
      107,
      0,
      47,
      3,
      61,
      62,
      24,
      142,
      1,
      0,
      4,
      17,
      34,
      15,
      0,
      186,
      0,
      18,
      47,
      8,
      1,
      23,
      114,
      0,
      0,
      0,
      16,
      40,
      16,
      14,
      42,
      57,
      7,
      59
    ],
    "intervention_topk": [
      [
        1,
        0.42857142857142855
      ],
      [
        2,
        0.5714285714285714
      ],
      [
        3,
        0.6904761904761905
      ]
    ],
    "intervention_rank_list": [
      118,
      2,
      0,
      0,
      2,
      0,
      7,
      127,
      0,
      0,
      11,
      0,
      2,
      2,
      4,
      26,
      0,
      0,
      1,
      0,
      4,
      1,
      0,
      72,
      0,
      2,
      7,
      1,
      0,
      0,
      45,
      0,
      0,
      0,
      1,
      0,
      6,
      0,
      34,
      7,
      1,
      1
    ]
  },
  "14": {
    "clean_topk": [
      [
        1,
        0.16666666666666666
      ],
      [
        2,
        0.21428571428571427
      ],
      [
        3,
        0.21428571428571427
      ]
    ],
    "clean_rank_list": [
      153,
      10,
      45,
      4,
      4,
      5,
      44,
      461,
      107,
      0,
      47,
      3,
      61,
      62,
      24,
      142,
      1,
      0,
      4,
      17,
      34,
      15,
      0,
      186,
      0,
      18,
      47,
      8,
      1,
      23,
      114,
      0,
      0,
      0,
      16,
      40,
      16,
      14,
      42,
      57,
      7,
      59
    ],
    "intervention_topk": [
      [
        1,
        0.23809523809523808
      ],
      [
        2,
        0.2857142857142857
      ],
      [
        3,
        0.30952380952380953
      ]
    ],
    "intervention_rank_list": [
      147,
      7,
      17,
      3,
      10,
      1,
      42,
      619,
      85,
      0,
      26,
      1,
      49,
      28,
      10,
      86,
      0,
      0,
      2,
      7,
      21,
      6,
      0,
      112,
      0,
      4,
      32,
      6,
      0,
      3,
      93,
      0,
      0,
      0,
      4,
      17,
      12,
      8,
      39,
      17,
      0,
      8
    ]
  },
  "15": {
    "clean_topk": [
      [
        1,
        0.16666666666666666
      ],
      [
        2,
        0.21428571428571427
      ],
      [
        3,
        0.21428571428571427
      ]
    ],
    "clean_rank_list": [
      153,
      10,
      45,
      4,
      4,
      5,
      44,
      461,
      107,
      0,
      47,
      3,
      61,
      62,
      24,
      142,
      1,
      0,
      4,
      17,
      34,
      15,
      0,
      186,
      0,
      18,
      47,
      8,
      1,
      23,
      114,
      0,
      0,
      0,
      16,
      40,
      16,
      14,
      42,
      57,
      7,
      59
    ],
    "intervention_topk": [
      [
        1,
        0.23809523809523808
      ],
      [
        2,
        0.2857142857142857
      ],
      [
        3,
        0.30952380952380953
      ]
    ],
    "intervention_rank_list": [
      154,
      6,
      24,
      5,
      9,
      1,
      35,
      572,
      87,
      0,
      32,
      1,
      28,
      36,
      6,
      88,
      0,
      0,
      2,
      6,
      14,
      7,
      0,
      175,
      0,
      16,
      27,
      12,
      0,
      13,
      98,
      0,
      0,
      0,
      7,
      17,
      13,
      4,
      28,
      17,
      0,
      8
    ]
  },
  "16": {
    "clean_topk": [
      [
        1,
        0.16666666666666666
      ],
      [
        2,
        0.21428571428571427
      ],
      [
        3,
        0.21428571428571427
      ]
    ],
    "clean_rank_list": [
      153,
      10,
      45,
      4,
      4,
      5,
      44,
      461,
      107,
      0,
      47,
      3,
      61,
      62,
      24,
      142,
      1,
      0,
      4,
      17,
      34,
      15,
      0,
      186,
      0,
      18,
      47,
      8,
      1,
      23,
      114,
      0,
      0,
      0,
      16,
      40,
      16,
      14,
      42,
      57,
      7,
      59
    ],
    "intervention_topk": [
      [
        1,
        0.2619047619047619
      ],
      [
        2,
        0.2857142857142857
      ],
      [
        3,
        0.3333333333333333
      ]
    ],
    "intervention_rank_list": [
      134,
      4,
      53,
      4,
      6,
      0,
      30,
      470,
      101,
      0,
      29,
      0,
      37,
      10,
      5,
      81,
      0,
      0,
      2,
      10,
      16,
      14,
      0,
      181,
      0,
      15,
      28,
      10,
      0,
      26,
      99,
      0,
      0,
      0,
      8,
      31,
      13,
      2,
      31,
      33,
      1,
      16
    ]
  },
  "17": {
    "clean_topk": [
      [
        1,
        0.16666666666666666
      ],
      [
        2,
        0.21428571428571427
      ],
      [
        3,
        0.21428571428571427
      ]
    ],
    "clean_rank_list": [
      153,
      10,
      45,
      4,
      4,
      5,
      44,
      461,
      107,
      0,
      47,
      3,
      61,
      62,
      24,
      142,
      1,
      0,
      4,
      17,
      34,
      15,
      0,
      186,
      0,
      18,
      47,
      8,
      1,
      23,
      114,
      0,
      0,
      0,
      16,
      40,
      16,
      14,
      42,
      57,
      7,
      59
    ],
    "intervention_topk": [
      [
        1,
        0.21428571428571427
      ],
      [
        2,
        0.23809523809523808
      ],
      [
        3,
        0.30952380952380953
      ]
    ],
    "intervention_rank_list": [
      152,
      10,
      36,
      2,
      4,
      4,
      42,
      519,
      101,
      0,
      35,
      1,
      42,
      13,
      11,
      76,
      0,
      0,
      2,
      18,
      26,
      12,
      0,
      192,
      0,
      19,
      20,
      8,
      0,
      20,
      108,
      0,
      0,
      0,
      12,
      46,
      17,
      7,
      42,
      45,
      2,
      52
    ]
  },
  "18": {
    "clean_topk": [
      [
        1,
        0.16666666666666666
      ],
      [
        2,
        0.21428571428571427
      ],
      [
        3,
        0.21428571428571427
      ]
    ],
    "clean_rank_list": [
      153,
      10,
      45,
      4,
      4,
      5,
      44,
      461,
      107,
      0,
      47,
      3,
      61,
      62,
      24,
      142,
      1,
      0,
      4,
      17,
      34,
      15,
      0,
      186,
      0,
      18,
      47,
      8,
      1,
      23,
      114,
      0,
      0,
      0,
      16,
      40,
      16,
      14,
      42,
      57,
      7,
      59
    ],
    "intervention_topk": [
      [
        1,
        0.19047619047619047
      ],
      [
        2,
        0.23809523809523808
      ],
      [
        3,
        0.30952380952380953
      ]
    ],
    "intervention_rank_list": [
      151,
      7,
      21,
      2,
      4,
      3,
      39,
      353,
      106,
      0,
      21,
      1,
      55,
      25,
      12,
      98,
      0,
      0,
      2,
      11,
      24,
      13,
      1,
      178,
      0,
      15,
      28,
      4,
      0,
      21,
      100,
      0,
      0,
      0,
      8,
      38,
      20,
      7,
      51,
      47,
      2,
      48
    ]
  },
  "19": {
    "clean_topk": [
      [
        1,
        0.16666666666666666
      ],
      [
        2,
        0.21428571428571427
      ],
      [
        3,
        0.21428571428571427
      ]
    ],
    "clean_rank_list": [
      153,
      10,
      45,
      4,
      4,
      5,
      44,
      461,
      107,
      0,
      47,
      3,
      61,
      62,
      24,
      142,
      1,
      0,
      4,
      17,
      34,
      15,
      0,
      186,
      0,
      18,
      47,
      8,
      1,
      23,
      114,
      0,
      0,
      0,
      16,
      40,
      16,
      14,
      42,
      57,
      7,
      59
    ],
    "intervention_topk": [
      [
        1,
        0.21428571428571427
      ],
      [
        2,
        0.23809523809523808
      ],
      [
        3,
        0.30952380952380953
      ]
    ],
    "intervention_rank_list": [
      155,
      8,
      21,
      2,
      4,
      3,
      36,
      329,
      121,
      0,
      27,
      1,
      55,
      36,
      16,
      84,
      0,
      0,
      2,
      13,
      37,
      15,
      0,
      174,
      0,
      11,
      22,
      4,
      0,
      16,
      105,
      0,
      0,
      0,
      12,
      33,
      17,
      11,
      41,
      55,
      2,
      42
    ]
  },
  "20": {
    "clean_topk": [
      [
        1,
        0.16666666666666666
      ],
      [
        2,
        0.21428571428571427
      ],
      [
        3,
        0.21428571428571427
      ]
    ],
    "clean_rank_list": [
      153,
      10,
      45,
      4,
      4,
      5,
      44,
      461,
      107,
      0,
      47,
      3,
      61,
      62,
      24,
      142,
      1,
      0,
      4,
      17,
      34,
      15,
      0,
      186,
      0,
      18,
      47,
      8,
      1,
      23,
      114,
      0,
      0,
      0,
      16,
      40,
      16,
      14,
      42,
      57,
      7,
      59
    ],
    "intervention_topk": [
      [
        1,
        0.21428571428571427
      ],
      [
        2,
        0.2619047619047619
      ],
      [
        3,
        0.30952380952380953
      ]
    ],
    "intervention_rank_list": [
      154,
      9,
      25,
      1,
      4,
      3,
      41,
      360,
      113,
      0,
      30,
      1,
      64,
      36,
      14,
      95,
      0,
      0,
      2,
      13,
      31,
      19,
      0,
      160,
      0,
      8,
      25,
      5,
      0,
      20,
      108,
      0,
      0,
      0,
      9,
      35,
      12,
      12,
      42,
      54,
      2,
      38
    ]
  },
  "21": {
    "clean_topk": [
      [
        1,
        0.16666666666666666
      ],
      [
        2,
        0.21428571428571427
      ],
      [
        3,
        0.21428571428571427
      ]
    ],
    "clean_rank_list": [
      153,
      10,
      45,
      4,
      4,
      5,
      44,
      461,
      107,
      0,
      47,
      3,
      61,
      62,
      24,
      142,
      1,
      0,
      4,
      17,
      34,
      15,
      0,
      186,
      0,
      18,
      47,
      8,
      1,
      23,
      114,
      0,
      0,
      0,
      16,
      40,
      16,
      14,
      42,
      57,
      7,
      59
    ],
    "intervention_topk": [
      [
        1,
        0.21428571428571427
      ],
      [
        2,
        0.23809523809523808
      ],
      [
        3,
        0.2619047619047619
      ]
    ],
    "intervention_rank_list": [
      157,
      9,
      34,
      3,
      5,
      3,
      47,
      357,
      110,
      0,
      30,
      1,
      72,
      48,
      15,
      95,
      0,
      0,
      2,
      18,
      31,
      18,
      0,
      154,
      0,
      10,
      32,
      5,
      0,
      19,
      105,
      0,
      0,
      0,
      14,
      40,
      14,
      14,
      52,
      54,
      3,
      47
    ]
  },
  "22": {
    "clean_topk": [
      [
        1,
        0.16666666666666666
      ],
      [
        2,
        0.21428571428571427
      ],
      [
        3,
        0.21428571428571427
      ]
    ],
    "clean_rank_list": [
      153,
      10,
      45,
      4,
      4,
      5,
      44,
      461,
      107,
      0,
      47,
      3,
      61,
      62,
      24,
      142,
      1,
      0,
      4,
      17,
      34,
      15,
      0,
      186,
      0,
      18,
      47,
      8,
      1,
      23,
      114,
      0,
      0,
      0,
      16,
      40,
      16,
      14,
      42,
      57,
      7,
      59
    ],
    "intervention_topk": [
      [
        1,
        0.21428571428571427
      ],
      [
        2,
        0.2619047619047619
      ],
      [
        3,
        0.2857142857142857
      ]
    ],
    "intervention_rank_list": [
      151,
      10,
      27,
      1,
      4,
      3,
      46,
      351,
      116,
      0,
      27,
      1,
      78,
      52,
      12,
      100,
      0,
      0,
      2,
      24,
      43,
      18,
      0,
      153,
      0,
      9,
      35,
      3,
      0,
      21,
      103,
      0,
      0,
      0,
      13,
      36,
      16,
      15,
      45,
      51,
      4,
      51
    ]
  },
  "23": {
    "clean_topk": [
      [
        1,
        0.16666666666666666
      ],
      [
        2,
        0.21428571428571427
      ],
      [
        3,
        0.21428571428571427
      ]
    ],
    "clean_rank_list": [
      153,
      10,
      45,
      4,
      4,
      5,
      44,
      461,
      107,
      0,
      47,
      3,
      61,
      62,
      24,
      142,
      1,
      0,
      4,
      17,
      34,
      15,
      0,
      186,
      0,
      18,
      47,
      8,
      1,
      23,
      114,
      0,
      0,
      0,
      16,
      40,
      16,
      14,
      42,
      57,
      7,
      59
    ],
    "intervention_topk": [
      [
        1,
        0.21428571428571427
      ],
      [
        2,
        0.23809523809523808
      ],
      [
        3,
        0.2857142857142857
      ]
    ],
    "intervention_rank_list": [
      143,
      9,
      34,
      4,
      9,
      2,
      41,
      380,
      102,
      0,
      28,
      1,
      83,
      48,
      13,
      101,
      0,
      0,
      2,
      26,
      38,
      19,
      0,
      146,
      0,
      10,
      32,
      3,
      0,
      25,
      105,
      0,
      0,
      0,
      15,
      36,
      14,
      15,
      43,
      54,
      4,
      55
    ]
  },
  "24": {
    "clean_topk": [
      [
        1,
        0.16666666666666666
      ],
      [
        2,
        0.21428571428571427
      ],
      [
        3,
        0.21428571428571427
      ]
    ],
    "clean_rank_list": [
      153,
      10,
      45,
      4,
      4,
      5,
      44,
      461,
      107,
      0,
      47,
      3,
      61,
      62,
      24,
      142,
      1,
      0,
      4,
      17,
      34,
      15,
      0,
      186,
      0,
      18,
      47,
      8,
      1,
      23,
      114,
      0,
      0,
      0,
      16,
      40,
      16,
      14,
      42,
      57,
      7,
      59
    ],
    "intervention_topk": [
      [
        1,
        0.19047619047619047
      ],
      [
        2,
        0.21428571428571427
      ],
      [
        3,
        0.23809523809523808
      ]
    ],
    "intervention_rank_list": [
      147,
      9,
      46,
      2,
      5,
      5,
      44,
      471,
      107,
      0,
      50,
      5,
      82,
      54,
      28,
      104,
      1,
      0,
      4,
      26,
      48,
      19,
      0,
      148,
      0,
      15,
      30,
      4,
      0,
      24,
      101,
      0,
      0,
      0,
      24,
      39,
      21,
      16,
      43,
      56,
      10,
      61
    ]
  },
  "25": {
    "clean_topk": [
      [
        1,
        0.16666666666666666
      ],
      [
        2,
        0.21428571428571427
      ],
      [
        3,
        0.21428571428571427
      ]
    ],
    "clean_rank_list": [
      153,
      10,
      45,
      4,
      4,
      5,
      44,
      461,
      107,
      0,
      47,
      3,
      61,
      62,
      24,
      142,
      1,
      0,
      4,
      17,
      34,
      15,
      0,
      186,
      0,
      18,
      47,
      8,
      1,
      23,
      114,
      0,
      0,
      0,
      16,
      40,
      16,
      14,
      42,
      57,
      7,
      59
    ],
    "intervention_topk": [
      [
        1,
        0.14285714285714285
      ],
      [
        2,
        0.23809523809523808
      ],
      [
        3,
        0.23809523809523808
      ]
    ],
    "intervention_rank_list": [
      146,
      9,
      42,
      1,
      4,
      5,
      40,
      468,
      105,
      0,
      52,
      6,
      68,
      48,
      29,
      107,
      1,
      1,
      4,
      26,
      47,
      21,
      1,
      180,
      0,
      16,
      36,
      6,
      0,
      23,
      88,
      0,
      0,
      0,
      22,
      41,
      20,
      17,
      45,
      58,
      8,
      66
    ]
  },
  "26": {
    "clean_topk": [
      [
        1,
        0.16666666666666666
      ],
      [
        2,
        0.21428571428571427
      ],
      [
        3,
        0.21428571428571427
      ]
    ],
    "clean_rank_list": [
      153,
      10,
      45,
      4,
      4,
      5,
      44,
      461,
      107,
      0,
      47,
      3,
      61,
      62,
      24,
      142,
      1,
      0,
      4,
      17,
      34,
      15,
      0,
      186,
      0,
      18,
      47,
      8,
      1,
      23,
      114,
      0,
      0,
      0,
      16,
      40,
      16,
      14,
      42,
      57,
      7,
      59
    ],
    "intervention_topk": [
      [
        1,
        0.11904761904761904
      ],
      [
        2,
        0.21428571428571427
      ],
      [
        3,
        0.21428571428571427
      ]
    ],
    "intervention_rank_list": [
      148,
      9,
      47,
      3,
      4,
      5,
      34,
      436,
      99,
      0,
      55,
      6,
      64,
      51,
      26,
      122,
      1,
      1,
      4,
      28,
      34,
      20,
      1,
      197,
      0,
      15,
      38,
      7,
      1,
      23,
      100,
      0,
      0,
      0,
      17,
      37,
      20,
      16,
      40,
      57,
      9,
      61
    ]
  },
  "27": {
    "clean_topk": [
      [
        1,
        0.16666666666666666
      ],
      [
        2,
        0.21428571428571427
      ],
      [
        3,
        0.21428571428571427
      ]
    ],
    "clean_rank_list": [
      153,
      10,
      45,
      4,
      4,
      5,
      44,
      461,
      107,
      0,
      47,
      3,
      61,
      62,
      24,
      142,
      1,
      0,
      4,
      17,
      34,
      15,
      0,
      186,
      0,
      18,
      47,
      8,
      1,
      23,
      114,
      0,
      0,
      0,
      16,
      40,
      16,
      14,
      42,
      57,
      7,
      59
    ],
    "intervention_topk": [
      [
        1,
        0.11904761904761904
      ],
      [
        2,
        0.21428571428571427
      ],
      [
        3,
        0.21428571428571427
      ]
    ],
    "intervention_rank_list": [
      145,
      9,
      53,
      3,
      4,
      5,
      34,
      452,
      99,
      0,
      46,
      6,
      62,
      56,
      26,
      115,
      1,
      1,
      4,
      25,
      32,
      20,
      1,
      200,
      0,
      17,
      37,
      8,
      1,
      25,
      102,
      0,
      0,
      0,
      18,
      35,
      17,
      16,
      44,
      56,
      8,
      69
    ]
  },
  "28": {
    "clean_topk": [
      [
        1,
        0.16666666666666666
      ],
      [
        2,
        0.21428571428571427
      ],
      [
        3,
        0.21428571428571427
      ]
    ],
    "clean_rank_list": [
      153,
      10,
      45,
      4,
      4,
      5,
      44,
      461,
      107,
      0,
      47,
      3,
      61,
      62,
      24,
      142,
      1,
      0,
      4,
      17,
      34,
      15,
      0,
      186,
      0,
      18,
      47,
      8,
      1,
      23,
      114,
      0,
      0,
      0,
      16,
      40,
      16,
      14,
      42,
      57,
      7,
      59
    ],
    "intervention_topk": [
      [
        1,
        0.14285714285714285
      ],
      [
        2,
        0.21428571428571427
      ],
      [
        3,
        0.21428571428571427
      ]
    ],
    "intervention_rank_list": [
      143,
      10,
      47,
      3,
      4,
      5,
      31,
      443,
      102,
      0,
      41,
      5,
      67,
      65,
      26,
      135,
      0,
      1,
      4,
      23,
      33,
      20,
      1,
      193,
      0,
      14,
      42,
      7,
      1,
      23,
      107,
      0,
      0,
      0,
      19,
      41,
      22,
      18,
      42,
      57,
      8,
      68
    ]
  },
  "29": {
    "clean_topk": [
      [
        1,
        0.16666666666666666
      ],
      [
        2,
        0.21428571428571427
      ],
      [
        3,
        0.21428571428571427
      ]
    ],
    "clean_rank_list": [
      153,
      10,
      45,
      4,
      4,
      5,
      44,
      461,
      107,
      0,
      47,
      3,
      61,
      62,
      24,
      142,
      1,
      0,
      4,
      17,
      34,
      15,
      0,
      186,
      0,
      18,
      47,
      8,
      1,
      23,
      114,
      0,
      0,
      0,
      16,
      40,
      16,
      14,
      42,
      57,
      7,
      59
    ],
    "intervention_topk": [
      [
        1,
        0.16666666666666666
      ],
      [
        2,
        0.21428571428571427
      ],
      [
        3,
        0.21428571428571427
      ]
    ],
    "intervention_rank_list": [
      143,
      11,
      49,
      3,
      4,
      5,
      30,
      414,
      108,
      0,
      50,
      4,
      58,
      60,
      29,
      135,
      0,
      0,
      4,
      25,
      31,
      19,
      1,
      167,
      0,
      15,
      42,
      7,
      1,
      21,
      115,
      0,
      0,
      0,
      18,
      42,
      21,
      17,
      40,
      58,
      8,
      62
    ]
  },
  "30": {
    "clean_topk": [
      [
        1,
        0.16666666666666666
      ],
      [
        2,
        0.21428571428571427
      ],
      [
        3,
        0.21428571428571427
      ]
    ],
    "clean_rank_list": [
      153,
      10,
      45,
      4,
      4,
      5,
      44,
      461,
      107,
      0,
      47,
      3,
      61,
      62,
      24,
      142,
      1,
      0,
      4,
      17,
      34,
      15,
      0,
      186,
      0,
      18,
      47,
      8,
      1,
      23,
      114,
      0,
      0,
      0,
      16,
      40,
      16,
      14,
      42,
      57,
      7,
      59
    ],
    "intervention_topk": [
      [
        1,
        0.16666666666666666
      ],
      [
        2,
        0.21428571428571427
      ],
      [
        3,
        0.23809523809523808
      ]
    ],
    "intervention_rank_list": [
      123,
      11,
      46,
      2,
      4,
      5,
      27,
      399,
      112,
      0,
      42,
      4,
      65,
      53,
      27,
      124,
      0,
      0,
      4,
      23,
      38,
      18,
      1,
      174,
      0,
      17,
      45,
      7,
      1,
      23,
      105,
      0,
      0,
      0,
      18,
      44,
      22,
      19,
      41,
      59,
      9,
      58
    ]
  },
  "31": {
    "clean_topk": [
      [
        1,
        0.16666666666666666
      ],
      [
        2,
        0.21428571428571427
      ],
      [
        3,
        0.21428571428571427
      ]
    ],
    "clean_rank_list": [
      153,
      10,
      45,
      4,
      4,
      5,
      44,
      461,
      107,
      0,
      47,
      3,
      61,
      62,
      24,
      142,
      1,
      0,
      4,
      17,
      34,
      15,
      0,
      186,
      0,
      18,
      47,
      8,
      1,
      23,
      114,
      0,
      0,
      0,
      16,
      40,
      16,
      14,
      42,
      57,
      7,
      59
    ],
    "intervention_topk": [
      [
        1,
        0.19047619047619047
      ],
      [
        2,
        0.21428571428571427
      ],
      [
        3,
        0.23809523809523808
      ]
    ],
    "intervention_rank_list": [
      133,
      13,
      41,
      2,
      4,
      4,
      32,
      422,
      123,
      0,
      38,
      4,
      82,
      52,
      25,
      124,
      0,
      0,
      4,
      17,
      42,
      17,
      1,
      183,
      0,
      21,
      48,
      8,
      0,
      20,
      113,
      0,
      0,
      0,
      19,
      45,
      19,
      21,
      38,
      58,
      9,
      57
    ]
  }
}